boston/__init__.py
boston/house.py
boston/resources/boston_house_prices.csv
boston/resources/descr.rst
boston-1.0.17.data/data/resources/boston_house_prices.csv
boston-1.0.17.dist-info/METADATA
boston-1.0.17.dist-info/WHEEL
boston-1.0.17.dist-info/top_level.txt
boston-1.0.17.dist-info/RECORD
