Metadata-Version: 2.1
Name: boston
Version: 1.0.17
Summary: loading boston housing price dataset like sklearn.datasets.load_boston() style.
Home-page: https://github.com/dltpdn/boston
Author: julmubm
Author-email: dltpdn@gmail.com
Classifier: Programming Language :: Python :: 3
Classifier: License :: OSI Approved :: MIT License
Classifier: Operating System :: OS Independent
Requires-Python: >=3.6
Requires-Dist: pandas
